README.md
setup.py
b26_toolkit/__init__.py
b26_toolkit.egg-info/PKG-INFO
b26_toolkit.egg-info/SOURCES.txt
b26_toolkit.egg-info/dependency_links.txt
b26_toolkit.egg-info/requires.txt
b26_toolkit.egg-info/top_level.txt
b26_toolkit/core/__init__.py
b26_toolkit/core/script_iterator.py
b26_toolkit/data_analysis/__init__.py
b26_toolkit/data_analysis/esr_plots.py
b26_toolkit/data_analysis/esr_post_processing.py
b26_toolkit/data_analysis/fields.py
b26_toolkit/data_analysis/fields_plot.py
b26_toolkit/data_analysis/nv_analysis.py
b26_toolkit/data_analysis/nv_optical_response.py
b26_toolkit/data_analysis/nv_optical_response_test.py
b26_toolkit/data_analysis/opencv_test.py
b26_toolkit/data_analysis/pair_nv_images.py
b26_toolkit/data_processing/__init__.py
b26_toolkit/data_processing/coordinate_conversions.py
b26_toolkit/data_processing/correlate_images.py
b26_toolkit/data_processing/create_figures.py
b26_toolkit/data_processing/esr_signal_processing.py
b26_toolkit/data_processing/fit_functions.py
b26_toolkit/data_processing/measurement.py
b26_toolkit/data_processing/temp.py
b26_toolkit/gui/__init__.py
b26_toolkit/gui/b26_gui.py
b26_toolkit/gui/b26_load_dialog.py
b26_toolkit/gui/b26_run_gui.py
b26_toolkit/instruments/__init__.py
b26_toolkit/instruments/attocube.py
b26_toolkit/instruments/awg.py
b26_toolkit/instruments/dcservo_thorlabs_kinesis.py
b26_toolkit/instruments/gauge_controller.py
b26_toolkit/instruments/keysight_oscilloscope.py
b26_toolkit/instruments/labview_fpga.py
b26_toolkit/instruments/maestro.py
b26_toolkit/instruments/magnet_coils.py
b26_toolkit/instruments/microwave_generator.py
b26_toolkit/instruments/montana.py
b26_toolkit/instruments/newport_smc100.py
b26_toolkit/instruments/ni_daq.py
b26_toolkit/instruments/piezo_controller.py
b26_toolkit/instruments/pulse_blaster.py
b26_toolkit/instruments/spectrum_analyzer.py
b26_toolkit/instruments/temperature_controller.py
b26_toolkit/instruments/thorlabs_kcube.py
b26_toolkit/instruments/ueye_camera.py
b26_toolkit/instruments/virtual_controler.py
b26_toolkit/instruments/zurich_instruments.py
b26_toolkit/plotting/__init__.py
b26_toolkit/plotting/plots_1d.py
b26_toolkit/plotting/plots_2d.py
