Metadata-Version: 1.1
Name: b26-toolkit
Version: 0.1a1
Summary: Python Laboratory Control Software
Home-page: https://github.com/LISE-B26/b26_toolkit
Author: Arthur Safira, Jan Gieseler, and Aaron Kabcenell
Author-email: asafira@fas.harvard.edu
License: GPL
Keywords: laboratory experiment control
Platform: UNKNOWN
Classifier: Programming Language :: Python :: 3.6
Classifier: License :: OSI Approved :: GNU General Public License v3 (GPLv3)
Classifier: Development Status :: 4 - Beta
Classifier: Environment :: Win32 (MS Windows)
